[
    {
        "イメージ": "<img src=\"https://www.wowkorea.jp/img/Profile/Movie/1/6000/4215_640.webp\"</img>",
        "内容": "<p>\n<b>鬼宮（ききゅう）</b>\nジャンル：ラブコメ\nキャスト：ユク・ソンジェ（BTOB）\n</p>"
    },
    {
        "イメージ": "<img src=\"https://www.wowkorea.jp/img/Profile/Movie/1/5998/4212_640.webp\"</img>",
        "内容": "<p>\n<b>いつかは賢いレジデント生活</b>\nジャンル：医療\nキャスト：コ・ユンジョン\n</p>"
    },
    {
        "イメージ": "<img src=\"https://www.wowkorea.jp/img/Profile/Movie/1/5999/4214_640.webp\"</img>",
        "内容": "<p>\n<b>君は天国でも美しい</b>\nジャンル：ラブコメ\nキャスト：キム・ヘジャ\n</p>"
    },
    {
        "イメージ": "<img src=\"https://www.wowkorea.jp/img/Profile/Movie/1/6019/4249_640.webp\"</img>",
        "内容": "<p>\n<b>禁酒をお願い</b>\nジャンル：ラブコメ\nキャスト：スヨン（少女時代）\n</p>"
    },
    {
        "イメージ": "<img src=\"https://www.wowkorea.jp/img/Profile/Movie/1/5997/4296_640.webp\"</img>",
        "内容": "<p>\n<b>24時ヘルスクラブ</b>\nジャンル：ラブコメ\nキャスト：イ・ジュニョン（元UKISS）\n</p>"
    }
]