[
    {
        "区分": "日経",
        "今日のニュース": "<a href=\"https://www.nikkei.com/article/DGKKZO91830090Z01C25A0MM8000/\" target=\"_blank\" rel=\"noopener noreferrer\">北川氏にノーベル化学賞金属有機構造体を開発\n脱炭素に寄与京大特別教授</a>"
    },
    {
        "区分": "AI",
        "今日のニュース": "<a href=\"https://www.itmedia.co.jp/aiplus/articles/2510/08/news061.html\" target=\"_blank\" rel=\"noopener noreferrer\">Google、PC操作を自動化するAI「Gemini2.5ComputerUse」のプレビュー版公開</a>"
    },
    {
        "区分": "エンタメ",
        "今日のニュース": "<a href=\"https://www.wowkorea.jp/news/read/503843.html\" target=\"_blank\" rel=\"noopener noreferrer\">「ASTRO」チャウヌ\nうれしい秋夕のあいさつ\n「また会う時まで元気で」</a>"
    },
    {
        "区分": "kpop",
        "今日のニュース": "<a href=\"https://www.wowkorea.jp/news/pickup/503948.html\" target=\"_blank\" rel=\"noopener noreferrer\">JENNIE(BLACKPINK) のパワー\nソウル観光で疾走\nBGMに「Seoul City」</a>"
    }
]